vulners_mcp/__init__.py
vulners_mcp/__main__.py
vulners_mcp/models.py
vulners_mcp/server.py
vulners_mcp/settings.py
vulners_mcp/vulners_client.py
vulners_mcp-1.0.3.dist-info/METADATA
vulners_mcp-1.0.3.dist-info/WHEEL
vulners_mcp-1.0.3.dist-info/RECORD
