Metadata-Version: 2.3
Name: vulners-mcp
Version: 1.0.3
Summary: MCP interface server fronting the Vulners API (https://vulners.com)
Keywords: MCP,security,network,vulners,vulnerability,CVE
Author: Vulners Team
Author-email: dev@vulners.com
Requires-Python: >=3.13,<4.0
Classifier: Programming Language :: Python :: 3
Classifier: Programming Language :: Python :: 3.13
Requires-Dist: fastmcp (>=2.12.3,<3.0.0)
Requires-Dist: httpx (>=0.28.1,<0.29.0)
Requires-Dist: mcp[cli] (>=1.9.0,<2.0)
Requires-Dist: pydantic (>=2.10,<3.0)
Requires-Dist: pydantic-ai (==0.0.13)
Requires-Dist: pydantic-settings (>=2.11.0,<3.0.0)
Requires-Dist: starlette (==0.39.2)
Requires-Dist: uvicorn (==0.30.6)
